maid_runner/__init__.py
maid_runner/__version__.py
maid_runner/py.typed
maid_runner/utils.py
maid_runner/validation_result.py
maid_runner/cache/__init__.py
maid_runner/cache/manifest_cache.py
maid_runner/claude/manifest.json
maid_runner/claude/agents/maid-auditor.md
maid_runner/claude/agents/maid-developer.md
maid_runner/claude/agents/maid-fixer.md
maid_runner/claude/agents/maid-manifest-architect.md
maid_runner/claude/agents/maid-plan-reviewer.md
maid_runner/claude/agents/maid-refactorer.md
maid_runner/claude/agents/maid-test-designer.md
maid_runner/claude/commands/audit.md
maid_runner/claude/commands/enhance-manifest.md
maid_runner/claude/commands/fix.md
maid_runner/claude/commands/generate-manifest.md
maid_runner/claude/commands/generate-tests.md
maid_runner/claude/commands/implement.md
maid_runner/claude/commands/improve-tests.md
maid_runner/claude/commands/maid-run.md
maid_runner/claude/commands/plan.md
maid_runner/claude/commands/pypi-release.md
maid_runner/claude/commands/quality-check-and-commit.md
maid_runner/claude/commands/refactor.md
maid_runner/claude/commands/run-validation.md
maid_runner/claude/commands/spike.md
maid_runner/claude/commands/validate-manifest.md
maid_runner/cli/__init__.py
maid_runner/cli/_batch_test_runner.py
maid_runner/cli/_behavioral_validation.py
maid_runner/cli/_manifest_helpers.py
maid_runner/cli/_test_file_extraction.py
maid_runner/cli/_validate_helpers.py
maid_runner/cli/files.py
maid_runner/cli/graph.py
maid_runner/cli/howto.py
maid_runner/cli/init.py
maid_runner/cli/list_manifests.py
maid_runner/cli/main.py
maid_runner/cli/manifest_create.py
maid_runner/cli/schema.py
maid_runner/cli/snapshot.py
maid_runner/cli/snapshot_system.py
maid_runner/cli/test.py
maid_runner/cli/validate.py
maid_runner/cli/init_tools/__init__.py
maid_runner/cli/init_tools/claude.py
maid_runner/cli/init_tools/cursor.py
maid_runner/cli/init_tools/generic.py
maid_runner/cli/init_tools/windsurf.py
maid_runner/coherence/__init__.py
maid_runner-0.11.4.dist-info/licenses/LICENSE
maid_runner-0.11.4.dist-info/METADATA
maid_runner-0.11.4.dist-info/WHEEL
maid_runner-0.11.4.dist-info/entry_points.txt
maid_runner-0.11.4.dist-info/top_level.txt
maid_runner-0.11.4.dist-info/RECORD
