Metadata-Version: 2.4
Name: maid-runner
Version: 0.11.4
Summary: Tool-agnostic validation framework for the Manifest-driven AI Development (MAID) methodology. Validates that code artifacts align with declarative manifests.
Author-email: "Mamerto Fabian Jr." <mamerto@codefrost.com>
License: MIT
Project-URL: Homepage, https://github.com/mamertofabian/maid-runner
Project-URL: Repository, https://github.com/mamertofabian/maid-runner
Project-URL: Issues, https://github.com/mamertofabian/maid-runner/issues
Project-URL: Documentation, https://github.com/mamertofabian/maid-runner#readme
Keywords: maid,validation,ai,development,manifest,tdd,architecture
Classifier: Development Status :: 4 - Beta
Classifier: Intended Audience :: Developers
Classifier: License :: OSI Approved :: MIT License
Classifier: Programming Language :: Python :: 3
Classifier: Programming Language :: Python :: 3.10
Classifier: Programming Language :: Python :: 3.11
Classifier: Programming Language :: Python :: 3.12
Classifier: Topic :: Software Development :: Quality Assurance
Classifier: Topic :: Software Development :: Testing
Classifier: Topic :: Software Development :: Libraries :: Python Modules
Requires-Python: >=3.10
License-File: LICENSE
Requires-Dist: jsonschema>=4.25.1
Requires-Dist: tree-sitter-svelte>=1.0.2
Requires-Dist: tree-sitter>=0.23.2
Requires-Dist: tree-sitter-typescript>=0.23.2
Provides-Extra: watch
Requires-Dist: watchdog>=6.0.0; extra == "watch"
Dynamic: license-file
